mlglass/__init__.py
mlglass/data/__init__.py
mlglass/data/dataGen.py
mlglass/data/load_data.py
mlglass/data/primitive_polynomials_GF2_dict.txt
mlglass/ml/LogisticRegression.py
mlglass/ml/Probabilistic.py
mlglass/ml/Trees.py
mlglass/ml/__init__.py
mlglass-0.0.1.dist-info/LICENSE
mlglass-0.0.1.dist-info/METADATA
mlglass-0.0.1.dist-info/WHEEL
mlglass-0.0.1.dist-info/top_level.txt
mlglass-0.0.1.dist-info/RECORD
