Metadata-Version: 2.1
Name: mlglass
Version: 0.0.1
Summary: MLglass: A Transparency with models
Home-page: https://github.com/Nikeshbajaj/mlglass
Author: Nikesh Bajaj
Author-email: bajaj.nikey@gmail.com
License: MIT
Download-URL: https://github.com/Nikeshbajaj/mlglass/tarball/0.0.1
Keywords: Machine Learning,Visualizations,Weights,Decision Tree,Naive Bayes
Platform: UNKNOWN
Classifier: Programming Language :: Python :: 3
Classifier: Programming Language :: Python :: 3.5
Classifier: Programming Language :: Python :: 3.6
Classifier: Programming Language :: Python :: 3.7
Classifier: License :: OSI Approved :: MIT License
Classifier: Operating System :: OS Independent
Classifier: Topic :: Scientific/Engineering :: Artificial Intelligence
Classifier: Topic :: Scientific/Engineering :: Information Analysis
Classifier: Topic :: Software Development :: Libraries :: Python Modules
Classifier: Intended Audience :: Developers
Classifier: Intended Audience :: Science/Research
Classifier: Development Status :: 5 - Production/Stable
Requires-Dist: numpy
Requires-Dist: matplotlib
Requires-Dist: scipy
Requires-Dist: scikit-learn
Requires-Dist: python-picard
